gptstream/__init__.py
gptstream/core.py
gptstream-0.1.0.dist-info/METADATA
gptstream-0.1.0.dist-info/WHEEL
gptstream-0.1.0.dist-info/top_level.txt
gptstream-0.1.0.dist-info/RECORD
