Metadata-Version: 2.1
Name: gptstream
Version: 0.1.0
Summary: OpenAI GPT Vision meets your webcam
Home-page: https://github.com/roboflow/gptstream
Author: Piotr Skalski
Author-email: piotr.skalski92@gmail.com
Classifier: Development Status :: 3 - Alpha
Classifier: Intended Audience :: Developers
Classifier: License :: OSI Approved :: MIT License
Classifier: Programming Language :: Python :: 3
Classifier: Programming Language :: Python :: 3.8
Classifier: Programming Language :: Python :: 3.9
Classifier: Programming Language :: Python :: 3.10
Classifier: Programming Language :: Python :: 3.11
Classifier: Programming Language :: Python :: 3 :: Only
Classifier: Topic :: Software Development :: Libraries :: Python Modules
Requires-Python: >=3.8,<3.12.0
Requires-Dist: supervision
Requires-Dist: openai
